LICENSE
MANIFEST.in
README.md
setup.cfg
setup.py
sqlbehave/__init__.py
sqlbehave/behavemodule.py
sqlbehave/testmodule.py
sqlbehave.egg-info/PKG-INFO
sqlbehave.egg-info/SOURCES.txt
sqlbehave.egg-info/dependency_links.txt
sqlbehave.egg-info/requires.txt
sqlbehave.egg-info/top_level.txt
sqlbehave/bin/sqlbehave-admin.py