Metadata-Version: 1.1
Name: sqlbehave
Version: 0.0.2.dev1
Summary: sqlbehave is behaviour-driven development based on Behave package
Home-page: https://github.com/AlexandrMov/sqlbehave
Author: Alexandr Movsunov
Author-email: sqlfuse@gmail.com
License: MIT
Keywords: bdd behave sql development testing
Platform: UNKNOWN
Classifier: Development Status :: 1 - Planning
Classifier: License :: OSI Approved :: MIT License
Classifier: Topic :: Software Development :: Testing
Classifier: Programming Language :: SQL
Classifier: Programming Language :: Python :: 3 :: Only
